setup.cfg
setup.py
mestpy/__init__.py
mestpy.egg-info/PKG-INFO
mestpy.egg-info/SOURCES.txt
mestpy.egg-info/dependency_links.txt
mestpy.egg-info/not-zip-safe
mestpy.egg-info/requires.txt
mestpy.egg-info/top_level.txt
mestpy/jordan_gauss/__init__.py
mestpy/jordan_gauss/artificial.py
mestpy/jordan_gauss/plain.py
mestpy/opop/__init__.py
mestpy/opop/work.py