Metadata-Version: 2.1
Name: mestpy
Version: 0.3.2
Summary: Gauss-Jordan Elimination in Teaching, Work with docs of main professional educational program
Home-page: UNKNOWN
Author: Mestnikov SV
Author-email: mestsv@mail.ru
License: UNKNOWN
Platform: UNKNOWN
Provides-Extra: interactive
